{
	"backtrace" : 0,
	"backtraceGraph" : 
	{
		"commands" : [],
		"files" : 
		[
			"ThirdParty/fastgltf/CMakeLists.txt"
		],
		"nodes" : 
		[
			{
				"file" : 0
			}
		]
	},
	"dependencies" : 
	[
		{
			"id" : "fastgltf::@fced6b4e3b39f7f1e5df"
		},
		{
			"id" : "ZERO_CHECK::@6890427a1f51a3e7e1df"
		}
	],
	"folder" : 
	{
		"name" : "CMakePredefinedTargets"
	},
	"id" : "ALL_BUILD::@fced6b4e3b39f7f1e5df",
	"isGeneratorProvided" : true,
	"name" : "ALL_BUILD",
	"paths" : 
	{
		"build" : "ThirdParty/fastgltf",
		"source" : "ThirdParty/fastgltf"
	},
	"sources" : [],
	"type" : "UTILITY"
}
